mitschreiben/__init__.py
mitschreiben/formatting.py
mitschreiben/recording.py
mitschreiben/table.py
mitschreiben/html_basics/accordion.html
mitschreiben/html_basics/accordion_tables_combined.html
mitschreiben/html_basics/tables.html
mitschreiben-0.3.dist-info/LICENSE
mitschreiben-0.3.dist-info/METADATA
mitschreiben-0.3.dist-info/WHEEL
mitschreiben-0.3.dist-info/top_level.txt
mitschreiben-0.3.dist-info/RECORD
